drew_imdb/__init__.py
drew_imdb/__main__.py
drew_imdb/api.py
drew_imdb/imdb.py
drew_imdb-0.1.1.dist-info/LICENSE
drew_imdb-0.1.1.dist-info/METADATA
drew_imdb-0.1.1.dist-info/WHEEL
drew_imdb-0.1.1.dist-info/entry_points.txt
drew_imdb-0.1.1.dist-info/top_level.txt
drew_imdb-0.1.1.dist-info/RECORD
