Metadata-Version: 2.1
Name: drew-imdb
Version: 0.1.1
Summary: A package that gets IMDb rating given an ID of a show, episode, or movie.
Author-email: Lawrence Sukova <lsukova@purdue.edu>
License: MIT License (MIT)
Keywords: example,IMDb,tutorial,API
Classifier: License :: OSI Approved :: MIT License
Classifier: Programming Language :: Python
Classifier: Programming Language :: Python :: 3
Classifier: Framework :: FastAPI
Requires-Python: >=3.10
License-File: LICENSE
Requires-Dist: lxml (>=4.9.1)
Requires-Dist: requests (>=2.28.1)
Requires-Dist: fastapi (>=0.85.2)
Requires-Dist: Jinja2 (>=3.1.2)
Requires-Dist: uvicorn[standard]
